setup.py
vmcontroller/__init__.py
vmcontroller.guest.egg-info/PKG-INFO
vmcontroller.guest.egg-info/SOURCES.txt
vmcontroller.guest.egg-info/dependency_links.txt
vmcontroller.guest.egg-info/entry_points.txt
vmcontroller.guest.egg-info/namespace_packages.txt
vmcontroller.guest.egg-info/not-zip-safe
vmcontroller.guest.egg-info/requires.txt
vmcontroller.guest.egg-info/top_level.txt
vmcontroller/guest/__init__.py
vmcontroller/guest/__main__.py
vmcontroller/guest/config/__init__.py
vmcontroller/guest/services/CommandExecuter.py
vmcontroller/guest/services/FileServer.py
vmcontroller/guest/services/VMStompEngine.py
vmcontroller/guest/services/VMWords.py
vmcontroller/guest/services/__init__.py