Metadata-Version: 1.0
Name: vmcontroller.guest
Version: 0.2.0
Summary: Virtual Machine Controller for guest operating system
Home-page: http://code.google.com/p/vmcontroller
Author: David Garcia Quintas, Rohit Yadav
Author-email: dgquintas@gmail.com, rohityadav89@gmail.com
License: BSD
Keywords: hypervisor virtual-machine controller
Platform: UNKNOWN
Classifier: Development Status :: 2 - Pre-Alpha
Classifier: Environment :: Console
Classifier: Intended Audience :: Developers
Classifier: License :: OSI Approved :: BSD License
Classifier: Operating System :: OS Independent
Classifier: Programming Language :: Python :: 2.6
Classifier: Topic :: Software Development :: Libraries :: Python Modules
